ADBox/BoxGUI.py
ADBox/BoxLdap.py
ADBox/BoxSearch.py
ADBox/BoxSql.py
ADBox/__init__.py
ADBox/__main__.py
ADBox/resources/__init__.py
ADBox/resources/adbox.png
ADBox/resources/computers.png
ADBox/resources/groups.png
ADBox/resources/users.png
ADBox-0.1.1.dist-info/LICENSE
ADBox-0.1.1.dist-info/METADATA
ADBox-0.1.1.dist-info/WHEEL
ADBox-0.1.1.dist-info/top_level.txt
ADBox-0.1.1.dist-info/RECORD
