Metadata-Version: 2.1
Name: ADBox
Version: 0.1.1
Summary: ADBox is a viewer for active directory objects.
Home-page: https://github.com/Ping-P0ng/ADBox
Author: Ping-P0ng
Author-email: 6xefe1d5@protonmail.com
License: UNKNOWN
Platform: UNKNOWN
Classifier: Programming Language :: Python :: 3
Classifier: License :: OSI Approved :: MIT License
License-File: LICENSE
Requires-Dist: ldap3 (==2.9.1)
Requires-Dist: PySide6 (==6.2.3)
